jupyterlab_slideshow/__init__.py
jupyterlab_slideshow/_version.py
jupyterlab_slideshow/tests/__init__.py
jupyterlab_slideshow/tests/test_metadata.py
jupyterlab_slideshow-0.3.4.data/data/share/jupyter/labextensions/jupyterlab-slideshow/package.json
jupyterlab_slideshow-0.3.4.data/data/share/jupyter/labextensions/jupyterlab-slideshow/schemas/jupyterlab-slideshow/package.json.orig
jupyterlab_slideshow-0.3.4.data/data/share/jupyter/labextensions/jupyterlab-slideshow/schemas/jupyterlab-slideshow/plugin.json
jupyterlab_slideshow-0.3.4.data/data/share/jupyter/labextensions/jupyterlab-slideshow/static/154.43c06597a236d339f88e.js
jupyterlab_slideshow-0.3.4.data/data/share/jupyter/labextensions/jupyterlab-slideshow/static/154.43c06597a236d339f88e.js.map
jupyterlab_slideshow-0.3.4.data/data/share/jupyter/labextensions/jupyterlab-slideshow/static/176.b8f064905a35ee9be0f4.js
jupyterlab_slideshow-0.3.4.data/data/share/jupyter/labextensions/jupyterlab-slideshow/static/176.b8f064905a35ee9be0f4.js.map
jupyterlab_slideshow-0.3.4.data/data/share/jupyter/labextensions/jupyterlab-slideshow/static/222.46e872667f9bbb142323.js
jupyterlab_slideshow-0.3.4.data/data/share/jupyter/labextensions/jupyterlab-slideshow/static/222.46e872667f9bbb142323.js.map
jupyterlab_slideshow-0.3.4.data/data/share/jupyter/labextensions/jupyterlab-slideshow/static/506.f6fdc59c43f36124bbff.js
jupyterlab_slideshow-0.3.4.data/data/share/jupyter/labextensions/jupyterlab-slideshow/static/506.f6fdc59c43f36124bbff.js.map
jupyterlab_slideshow-0.3.4.data/data/share/jupyter/labextensions/jupyterlab-slideshow/static/568.c2e36d5bbaa8488aaf5d.js
jupyterlab_slideshow-0.3.4.data/data/share/jupyter/labextensions/jupyterlab-slideshow/static/568.c2e36d5bbaa8488aaf5d.js.map
jupyterlab_slideshow-0.3.4.data/data/share/jupyter/labextensions/jupyterlab-slideshow/static/82.20b3c06c1800ea97d357.js
jupyterlab_slideshow-0.3.4.data/data/share/jupyter/labextensions/jupyterlab-slideshow/static/82.20b3c06c1800ea97d357.js.map
jupyterlab_slideshow-0.3.4.dist-info/licenses/LICENSE
jupyterlab_slideshow-0.3.4.dist-info/WHEEL
jupyterlab_slideshow-0.3.4.dist-info/METADATA
jupyterlab_slideshow-0.3.4.dist-info/RECORD
