Metadata-Version: 2.4
Name: jupyterlab-slideshow
Version: 0.3.4
Summary: A lightweight presentation mode for JupyterLab.
Requires-Python: >=3.8
Classifier: Framework :: Jupyter :: JupyterLab :: 3
Classifier: Framework :: Jupyter :: JupyterLab :: 4
Classifier: Framework :: Jupyter :: JupyterLab :: Extensions :: Prebuilt
Classifier: Framework :: Jupyter :: JupyterLab :: Extensions
Classifier: Framework :: Jupyter :: JupyterLab
Classifier: Framework :: Jupyter
Classifier: License :: OSI Approved :: BSD License
Classifier: Programming Language :: Python :: 3 :: Only
Classifier: Programming Language :: Python :: 3
License-File: LICENSE
Requires-Dist: jupyterlab >=4.1,<5.0.0a0
Requires-Dist: jupyterlab-fonts >=3.0.0
Project-URL: Bug Tracker, https://github.com/jupyterlab-contrib/jupyterlab-slideshow/issues
Project-URL: Changelog, https://github.com/jupyterlab-contrib/jupyterlab-slideshow/blob/main/CHANGELOG.md
Project-URL: Documentation, https://jupyterlab-deck.rtfd.io
Project-URL: Source, https://github.com/jupyterlab-contrib/jupyterlab-slideshow
